{"slug":"ᛒ-berkano","name":"ᛒ Berkano","kind":"other","icon":"✺","subtitle":"","summary":"Birth, nurture, growth, mothering","flowText":"Berkano is the green cradle — the crescent that becomes a garden.","families":["alchemical","chakras","colors","elements","frequencies","geometry","i-ching","kabbalah","letter","mayan","metals","other","physiology","plants"],"systemsSummary":{"colors":["Green","Pink"],"chakras":["Sacral","Heart"],"frequencies":["210 Hz"],"kabbalah":["Daleth (door of life) via Gimel (lunar passage)"],"letter":["Daleth","Gimel"],"i-ching":["☴ Wind","☵ Water"],"mayan":["Ix (jaguar, fertility)"],"elements":["Earth","Water"],"alchemical":["Dissolution (soften) → Conjunction (gestate)"],"metals":["Copper","Silver"],"plants":["Birch","Rose"],"geometry":["Birch branches","Crescent"],"physiology":["Womb","Breasts"]},"overview":[{"key":"essence","label":"Essence","value":"Birth, nurture, growth, mothering"},{"key":"element","label":"Element","value":"Earth · Water"},{"key":"chakra","label":"Chakras","value":"Sacral · Heart"},{"key":"color","label":"Colors","value":"Green · Pink"},{"key":"frequency","label":"Frequencies","value":"210 Hz"},{"key":"geometry","label":"Geometry","value":"Birch branches · Crescent"},{"key":"physiology","label":"Physiology","value":"Womb · Breasts"},{"key":"planet","label":"Planets","value":"Venus · Moon"},{"key":"zodiac","label":"Zodiac","value":"Taurus · Cancer"},{"key":"kabbalah","label":"Kabbalah","value":"Daleth (door of life) via Gimel (lunar passage)"},{"key":"hebrew letter","label":"Hebrew Letters","value":"Daleth · Gimel"},{"key":"tarot","label":"Tarot","value":"III The Empress · II The High Priestess"},{"key":"i ching","label":"I‑Ching","value":"☴ Wind · ☵ Water"},{"key":"mayan echo","label":"Mayan Echo","value":"Ix (jaguar, fertility)"},{"key":"processes","label":"Processes","value":"Dissolution (soften) → Conjunction (gestate)"},{"key":"metals","label":"Metals","value":"Copper · Silver"},{"key":"plants","label":"Plants","value":"Birch · Rose"}],"sections":[{"title":"Core","items":[{"label":"Essence","value":"Birth, nurture, growth, mothering"},{"label":"Element","value":"Earth/Water"},{"label":"Colors","value":"Green · Pink"},{"label":"Frequencies","value":"210 Hz"},{"label":"Note","value":"A3"},{"label":"Geometry / Symbolism","value":"Birch branches · Crescent"},{"label":"Physiology","value":"Womb · Breasts"}]},{"title":"Astrological / Planetary","items":[{"label":"Planets","value":"Venus · Moon"},{"label":"Zodiac","value":"Taurus · Cancer"},{"label":"Kabbalah","value":"Daleth (door of life) via Gimel (lunar passage)"},{"label":"Hebrew Letters","value":"Daleth · Gimel"},{"label":"Tarot","value":"III The Empress · II The High Priestess"}]},{"title":"Cross-System","items":[{"label":"I Ching","value":"☴ Wind · ☵ Water"},{"label":"Geomancy","value":"Puella (beauty) · Populus (gathering)"},{"label":"Metals","value":"Copper · Silver"},{"label":"Crystals","value":"Rose Quartz · Moonstone"},{"label":"Body","value":"Womb · Lymph"},{"label":"Chakras","value":"Sacral/Heart"},{"label":"Magical Tools","value":"Chalice · Cradle"},{"label":"Mayan Echo","value":"Ix (jaguar, fertility)"},{"label":"Keywords","value":"Birch · Birth · Growth"}]},{"title":"Alchemical / Material","items":[{"label":"Processes","value":"Dissolution (soften) → Conjunction (gestate)"},{"label":"Plants","value":"Birch · Rose"},{"label":"Deities/Angels","value":"Frigg · Freyja · Haniel"}]}],"related":[{"slug":"pluto","name":"♇ Pluto","kind":"planet","icon":"♇","score":16,"teaser":"Pluto is the black sun — furnace of death, seed of rebirth, fire of shadows."},{"slug":"freyja","name":"Freyja","kind":"deity","icon":"✧","score":15,"teaser":"Freyja embodies fertility, love, prosperity — under Venus; in Taurus."},{"slug":"venus","name":"♀ Venus","kind":"planet","icon":"♀","score":14,"teaser":"Venus is the rose of harmony — magnetic union, pulse of beauty, lover’s path."},{"slug":"zephyrus","name":"Zephyrus","kind":"other","icon":"✺","score":13,"teaser":"Heart is the vesica of the world — the overlap where differences become devotion."},{"slug":"freyr","name":"Freyr","kind":"deity","icon":"✧","score":12,"teaser":"Freyr embodies fertility, love, prosperity — under Venus; in Taurus."},{"slug":"numbers","name":"NUMBERS","kind":"other","icon":"✺","score":12,"teaser":"Monad is the point before all division — the radiant seed, the single flame from which the ten thousand things unfold."},{"slug":"moonstone","name":"Moonstone","kind":"crystal","icon":"✦","score":12,"teaser":"Sacral is the river—pleasure, creation, and the moon’s pull in the blood."},{"slug":"cancer","name":"♋ Cancer","kind":"zodiac","icon":"♋","score":12,"teaser":"Cancer is the lunar tide — mother’s embrace, ocean of feeling, mirror of psyche."},{"slug":"jarilo","name":"Jarilo","kind":"other","icon":"✺","score":11,"teaser":"Jarilo embodies spring, descent and return — under Venus; in Virgo, Pisces."},{"slug":"persephone","name":"Persephone","kind":"other","icon":"✺","score":11,"teaser":"Persephone embodies spring, descent and return — under Venus; in Virgo, Pisces."},{"slug":"frigg","name":"Frigg","kind":"deity","icon":"✧","score":11,"teaser":"Frigg embodies sovereign marriage, order, oaths — under Juno/Venus · Jupiter; in Libra."},{"slug":"proserpina","name":"Proserpina","kind":"other","icon":"✺","score":11,"teaser":"Proserpina embodies spring, descent and return — under Venus; in Virgo, Pisces."}],"badges":["Sacral","Heart","210 Hz","Venus","Moon","Taurus"]}