{"slug":"seven-of-wands","name":"Seven of Wands","kind":"tarot","icon":"🂠","subtitle":"","summary":"Challenge, vision, reevaluation of Fire. Assess motive, clarity over confusion.","flowText":"Seven of Wands is the wand of fire — Assess motive; clarity over confusion.","families":["alchemical","colors","elements","emotional","frequencies","geometry","i-ching","kabbalah","metals","numbers","physiology","plants","runes","tarot"],"systemsSummary":{"colors":["Red","Gold"],"frequencies":["172.06 Hz"],"kabbalah":["Netzach of Atziluth"],"i-ching":["☲ Li (Fire)","☳ Zhen (Thunder)"],"elements":["Fire"],"alchemical":["Fermentation","Desire"],"metals":["Gold","Iron"],"plants":["Ginger","Bay"],"geometry":["Triangle","Tetrahedron"],"numbers":["7"],"physiology":["Solar plexus","Circulation"],"runes":["Kenaz","Sowilo","Tiwaz"]},"overview":[{"key":"essence","label":"Essence","value":"Challenge · vision · reevaluation of Fire. Assess motive · clarity over confusion."},{"key":"element","label":"Element","value":"Fire"},{"key":"color","label":"Colors","value":"Red · Gold"},{"key":"frequency","label":"Frequencies","value":"172.06 Hz"},{"key":"geometry","label":"Geometry","value":"Triangle · Tetrahedron"},{"key":"physiology","label":"Physiology","value":"Solar plexus · Circulation"},{"key":"kabbalah","label":"Kabbalah","value":"Netzach of Atziluth"},{"key":"tarot","label":"Tarot","value":"XIX The Sun · VII The Chariot · XVI The Tower"},{"key":"runes","label":"Runes","value":"Kenaz · Sowilo · Tiwaz"},{"key":"i ching","label":"I‑Ching","value":"☲ Li (Fire) · ☳ Zhen (Thunder)"},{"key":"processes","label":"Processes","value":"Fermentation · Desire"},{"key":"metals","label":"Metals","value":"Gold · Iron"},{"key":"plants","label":"Plants","value":"Ginger · Bay"},{"key":"numbers","label":"Numbers","value":"7"}],"sections":[{"title":"Core","items":[{"label":"Essence","value":"Challenge/vision; reevaluation of Fire. Assess motive; clarity over confusion."},{"label":"Element","value":"Fire"},{"label":"Colors","value":"Red · Gold"},{"label":"Geometry / Symbolism","value":"Triangle · Tetrahedron"},{"label":"Frequencies","value":"172.06 Hz"},{"label":"Notes","value":"F"},{"label":"Physiology","value":"Solar plexus · Circulation"}]},{"title":"Astrological / Planetary","items":[{"label":"Planet/Zodiac","value":"Sun · Mars · Aries · Leo · Sagittarius"},{"label":"Kabbalah","value":"Netzach of Atziluth"},{"label":"Tarot Major Echo","value":"XIX The Sun · VII The Chariot · XVI The Tower"}]},{"title":"Cross-System","items":[{"label":"Runes","value":"Kenaz · Sowilo · Tiwaz"},{"label":"I Ching","value":"☲ Li (Fire) · ☳ Zhen (Thunder)"},{"label":"Geomancy","value":"Fortuna Major · Rubeus"},{"label":"Magical Tool","value":"Wand · Staff"},{"label":"Numbers","value":"7"}]},{"title":"Alchemical / Material","items":[{"label":"Processes","value":"Fermentation/Desire"},{"label":"Metals","value":"Gold · Iron"},{"label":"Crystals","value":"Sunstone · Carnelian"},{"label":"Materia Magica","value":"Ginger · Bay"}]}],"related":[{"slug":"queen-of-wands","name":"Queen of Wands","kind":"tarot","icon":"🂠","score":21,"teaser":"Queen of Wands is the wand of fire — Contain and cultivate; depth with discernment."},{"slug":"king-of-wands","name":"King of Wands","kind":"tarot","icon":"🂠","score":21,"teaser":"King of Wands is the wand of fire — Set order and direction; steward the realm."},{"slug":"nine-of-wands","name":"Nine of Wands","kind":"tarot","icon":"🂠","score":21,"teaser":"Nine of Wands is the wand of fire — Satisfaction and sovereignty; inner harvest."},{"slug":"four-of-wands","name":"Four of Wands","kind":"tarot","icon":"🂠","score":21,"teaser":"Four of Wands is the wand of fire — Structure and rest; beware stagnation."},{"slug":"five-of-wands","name":"Five of Wands","kind":"tarot","icon":"🂠","score":21,"teaser":"Five of Wands is the wand of fire — Friction reveals truth; growth through test."},{"slug":"pluto","name":"♇ Pluto","kind":"planet","icon":"♇","score":21,"teaser":"Pluto is the black sun — furnace of death, seed of rebirth, fire of shadows."},{"slug":"page-of-wands","name":"Page of Wands","kind":"tarot","icon":"🂠","score":21,"teaser":"Page of Wands is the wand of fire — Beginner’s mind; bring news and curiosity."},{"slug":"ten-of-wands","name":"Ten of Wands","kind":"tarot","icon":"🂠","score":21,"teaser":"Ten of Wands is the wand of fire — Completion and consequence; passing the mantle."},{"slug":"three-of-wands","name":"Three of Wands","kind":"tarot","icon":"🂠","score":21,"teaser":"Three of Wands is the wand of fire — Creation takes shape; teamwork with the element."},{"slug":"eight-of-wands","name":"Eight of Wands","kind":"tarot","icon":"🂠","score":21,"teaser":"Eight of Wands is the wand of fire — Skill and dedication; steady refinement."},{"slug":"six-of-wands","name":"Six of Wands","kind":"tarot","icon":"🂠","score":21,"teaser":"Six of Wands is the wand of fire — Reciprocity and grace; the current flows."},{"slug":"ace-of-wands","name":"Ace of Wands","kind":"tarot","icon":"🂠","score":21,"teaser":"Ace of Wands is the wand of fire — Origin essence — the {flow_noun} offered by the unseen."}],"badges":["172.06 Hz","Netzach of Atziluth","Triangle","Tetrahedron","Fermentation","Desire"]}